{"North America":{"Total Cases":"1,591,647","New Cases":"+21,761","Total Deaths":"97,220","New Deaths":"+1,753","Total Recovered":"388,567","Active Cases":"1,105,860","Serious\/Critical":"17,431","Tot Cases\/ 1M pop":0,"Deaths\/ 1M pop":0,"Total Tests":0,"Tests\/  1M pop ":0,"Continent":"North America"},"Europe":{"Total Cases":"1,718,303","New Cases":"+21,982","Total Deaths":"159,039","New Deaths":"+1,666","Total Recovered":"721,932","Active Cases":"837,332","Serious\/Critical":"12,533","Tot Cases\/ 1M pop":0,"Deaths\/ 1M pop":0,"Total Tests":0,"Tests\/  1M pop ":0,"Continent":"Europe"},"South America":{"Total Cases":"366,829","New Cases":"+11,538","Total Deaths":"19,536","New Deaths":"+511","Total Recovered":"128,829","Active Cases":"218,464","Serious\/Critical":"10,293","Tot Cases\/ 1M pop":0,"Deaths\/ 1M pop":0,"Total Tests":0,"Tests\/  1M pop ":0,"Continent":"South America"},"Asia":{"Total Cases":"738,737","New Cases":"+17,854","Total Deaths":"23,573","New Deaths":"+314","Total Recovered":"416,136","Active Cases":"299,028","Serious\/Critical":"4,952","Tot Cases\/ 1M pop":0,"Deaths\/ 1M pop":0,"Total Tests":0,"Tests\/  1M pop ":0,"Continent":"Asia"},"Africa":{"Total Cases":"76,027","New Cases":"+2,054","Total Deaths":"2,563","New Deaths":"+56","Total Recovered":"27,736","Active Cases":"45,728","Serious\/Critical":"258","Tot Cases\/ 1M pop":0,"Deaths\/ 1M pop":0,"Total Tests":0,"Tests\/  1M pop ":0,"Continent":"Africa"},"Oceania":{"Total Cases":"8,590","New Cases":"+9","Total Deaths":"119","New Deaths":0,"Total Recovered":"7,810","Active Cases":"661","Serious\/Critical":"21","Tot Cases\/ 1M pop":0,"Deaths\/ 1M pop":0,"Total Tests":0,"Tests\/  1M pop ":0,"Continent":"Australia\/Oceania"},"0":{"Total Cases":"721","New Cases":0,"Total Deaths":"15","New Deaths":0,"Total Recovered":"651","Active Cases":"55","Serious\/Critical":"4","Tot Cases\/ 1M pop":0,"Deaths\/ 1M pop":0,"Total Tests":0,"Tests\/  1M pop ":0,"Continent":0},"World":{"Total Cases":"4,500,854","New Cases":"+75,198","Total Deaths":"302,065","New Deaths":"+4,300","Total Recovered":"1,691,661","Active Cases":"2,507,128","Serious\/Critical":"45,492","Tot Cases\/ 1M pop":"577","Deaths\/ 1M pop":"38.8","Total Tests":0,"Tests\/  1M pop ":0,"Continent":"All"},"USA":{"Total Cases":"1,448,460","New Cases":"+18,112","Total Deaths":"86,468 ","New Deaths":"+1,271","Total Recovered":"312,535","Active Cases":"1,049,457","Serious\/Critical":"16,252","Tot Cases\/ 1M pop":"4,376","Deaths\/ 1M pop":"261","Total Tests":"10,516,577","Tests\/  1M pop ":"31,772","Continent":"North America"},"Spain":{"Total Cases":"272,646","New Cases":"+1,551","Total Deaths":"27,321 ","New Deaths":"+217","Total Recovered":"186,480","Active Cases":"58,845","Serious\/Critical":"1,376","Tot Cases\/ 1M pop":"5,831","Deaths\/ 1M pop":"584","Total Tests":"2,467,761","Tests\/  1M pop ":"52,781","Continent":"Europe"},"Russia":{"Total Cases":"252,245","New Cases":"+9,974","Total Deaths":"2,305 ","New Deaths":"+93","Total Recovered":"53,530","Active Cases":"196,410","Serious\/Critical":"2,300","Tot Cases\/ 1M pop":"1,728","Deaths\/ 1M pop":"16","Total Tests":"6,188,102","Tests\/  1M pop ":"42,403","Continent":"Europe"},"UK":{"Total Cases":"233,151","New Cases":"+3,446","Total Deaths":"33,614 ","New Deaths":"+428","Total Recovered":"N\/A","Active Cases":"199,193","Serious\/Critical":"1,559","Tot Cases\/ 1M pop":"3,434","Deaths\/ 1M pop":"495","Total Tests":"2,219,281","Tests\/  1M pop ":"32,691","Continent":"Europe"},"Italy":{"Total Cases":"223,096","New Cases":"+992","Total Deaths":"31,368 ","New Deaths":"+262","Total Recovered":"115,288","Active Cases":"76,440","Serious\/Critical":"855","Tot Cases\/ 1M pop":"3,690","Deaths\/ 1M pop":"519","Total Tests":"2,807,504","Tests\/  1M pop ":"46,434","Continent":"Europe"},"Brazil":{"Total Cases":"197,838","New Cases":"+8,681","Total Deaths":"13,618 ","New Deaths":"+460","Total Recovered":"78,424","Active Cases":"105,796","Serious\/Critical":"8,318","Tot Cases\/ 1M pop":"931","Deaths\/ 1M pop":"64","Total Tests":"735,224","Tests\/  1M pop ":"3,459","Continent":"South America"},"France":{"Total Cases":"178,870","New Cases":"+810","Total Deaths":"27,425 ","New Deaths":"+351","Total Recovered":"59,605","Active Cases":"91,840","Serious\/Critical":"2,299","Tot Cases\/ 1M pop":"2,740","Deaths\/ 1M pop":"420","Total Tests":"1,384,633","Tests\/  1M pop ":"21,213","Continent":"Europe"},"Germany":{"Total Cases":"174,636","New Cases":"+538","Total Deaths":"7,900 ","New Deaths":"+39","Total Recovered":"150,300","Active Cases":"16,436","Serious\/Critical":"1,329","Tot Cases\/ 1M pop":"2,084","Deaths\/ 1M pop":"94","Total Tests":"3,147,771","Tests\/  1M pop ":"37,570","Continent":"Europe"},"Turkey":{"Total Cases":"144,749","New Cases":"+1,635","Total Deaths":"4,007 ","New Deaths":"+55","Total Recovered":"104,030","Active Cases":"36,712","Serious\/Critical":"963","Tot Cases\/ 1M pop":"1,716","Deaths\/ 1M pop":"48","Total Tests":"1,508,824","Tests\/  1M pop ":"17,890","Continent":"Asia"},"Iran":{"Total Cases":"114,533","New Cases":"+1,808","Total Deaths":"6,854 ","New Deaths":"+71","Total Recovered":"90,539","Active Cases":"17,140","Serious\/Critical":"2,758","Tot Cases\/ 1M pop":"1,364","Deaths\/ 1M pop":"82","Total Tests":"643,772","Tests\/  1M pop ":"7,665","Continent":"Asia"},"India":{"Total Cases":"81,990","New Cases":"+3,935","Total Deaths":"2,649 ","New Deaths":"+98","Total Recovered":"27,969","Active Cases":"51,372","Serious\/Critical":0,"Tot Cases\/ 1M pop":"59","Deaths\/ 1M pop":"2","Total Tests":"1,947,041","Tests\/  1M pop ":"1,411","Continent":"Asia"},"Peru":{"Total Cases":"76,306","New Cases":0,"Total Deaths":"2,169 ","New Deaths":0,"Total Recovered":"24,324","Active Cases":"49,813","Serious\/Critical":"806","Tot Cases\/ 1M pop":"2,314","Deaths\/ 1M pop":"66","Total Tests":"553,302","Tests\/  1M pop ":"16,781","Continent":"South America"},"Canada":{"Total Cases":"73,335","New Cases":"+1,057","Total Deaths":"5,468 ","New Deaths":"+166","Total Recovered":"35,936","Active Cases":"31,931","Serious\/Critical":"502","Tot Cases\/ 1M pop":"1,943","Deaths\/ 1M pop":"145","Total Tests":"1,169,380","Tests\/  1M pop ":"30,983","Continent":"North America"},"Belgium":{"Total Cases":"54,288","New Cases":"+307","Total Deaths":"8,903 ","New Deaths":"+60","Total Recovered":"14,111","Active Cases":"31,274","Serious\/Critical":"407","Tot Cases\/ 1M pop":"4,684","Deaths\/ 1M pop":"768","Total Tests":"623,628","Tests\/  1M pop ":"53,809","Continent":"Europe"},"Saudi Arabia":{"Total Cases":"46,869","New Cases":"+2,039","Total Deaths":"283 ","New Deaths":"+10","Total Recovered":"19,051","Active Cases":"27,535","Serious\/Critical":"156","Tot Cases\/ 1M pop":"1,346","Deaths\/ 1M pop":"8","Total Tests":"513,587","Tests\/  1M pop ":"14,752","Continent":"Asia"},"Netherlands":{"Total Cases":"43,481","New Cases":"+270","Total Deaths":"5,590 ","New Deaths":"+28","Total Recovered":"N\/A","Active Cases":"37,641","Serious\/Critical":"410","Tot Cases\/ 1M pop":"2,538","Deaths\/ 1M pop":"326","Total Tests":"282,776","Tests\/  1M pop ":"16,503","Continent":"Europe"},"Mexico":{"Total Cases":"40,186","New Cases":"+1,862","Total Deaths":"4,220 ","New Deaths":"+294","Total Recovered":"26,990","Active Cases":"8,976","Serious\/Critical":"378","Tot Cases\/ 1M pop":"312","Deaths\/ 1M pop":"33","Total Tests":"142,204","Tests\/  1M pop ":"1,103","Continent":"North America"},"Chile":{"Total Cases":"37,040","New Cases":"+2,659","Total Deaths":"368 ","New Deaths":"+22","Total Recovered":"15,655","Active Cases":"21,017","Serious\/Critical":"663","Tot Cases\/ 1M pop":"1,938","Deaths\/ 1M pop":"19","Total Tests":"325,417","Tests\/  1M pop ":"17,023","Continent":"South America"},"Pakistan":{"Total Cases":"35,788","New Cases":"+490","Total Deaths":"770 ","New Deaths":"+9","Total Recovered":"9,695","Active Cases":"25,323","Serious\/Critical":"111","Tot Cases\/ 1M pop":"162","Deaths\/ 1M pop":"3","Total Tests":"330,750","Tests\/  1M pop ":"1,497","Continent":"Asia"},"Ecuador":{"Total Cases":"30,486","New Cases":0,"Total Deaths":"2,334 ","New Deaths":0,"Total Recovered":"3,433","Active Cases":"24,719","Serious\/Critical":"190","Tot Cases\/ 1M pop":"1,728","Deaths\/ 1M pop":"132","Total Tests":"87,036","Tests\/  1M pop ":"4,933","Continent":"South America"},"Switzerland":{"Total Cases":"30,463","New Cases":"+50","Total Deaths":"1,872 ","New Deaths":"+2","Total Recovered":"27,100","Active Cases":"1,491","Serious\/Critical":"79","Tot Cases\/ 1M pop":"3,520","Deaths\/ 1M pop":"216","Total Tests":"328,163","Tests\/  1M pop ":"37,918","Continent":"Europe"},"Sweden":{"Total Cases":"28,582","New Cases":"+673","Total Deaths":"3,529 ","New Deaths":"+69","Total Recovered":"4,971","Active Cases":"20,082","Serious\/Critical":"351","Tot Cases\/ 1M pop":"2,830","Deaths\/ 1M pop":"349","Total Tests":"177,500","Tests\/  1M pop ":"17,576","Continent":"Europe"},"Portugal":{"Total Cases":"28,319","New Cases":"+187","Total Deaths":"1,184 ","New Deaths":"+9","Total Recovered":"3,198","Active Cases":"23,937","Serious\/Critical":"108","Tot Cases\/ 1M pop":"2,777","Deaths\/ 1M pop":"116","Total Tests":"582,341","Tests\/  1M pop ":"57,111","Continent":"Europe"},"Qatar":{"Total Cases":"28,272","New Cases":"+1,733","Total Deaths":"14 ","New Deaths":0,"Total Recovered":"3,356","Active Cases":"24,902","Serious\/Critical":"72","Tot Cases\/ 1M pop":"9,813","Deaths\/ 1M pop":"5","Total Tests":"143,938","Tests\/  1M pop ":"49,960","Continent":"Asia"},"Belarus":{"Total Cases":"26,772","New Cases":"+947","Total Deaths":"151 ","New Deaths":"+5","Total Recovered":"8,168","Active Cases":"18,453","Serious\/Critical":"92","Tot Cases\/ 1M pop":"2,833","Deaths\/ 1M pop":"16","Total Tests":"308,156","Tests\/  1M pop ":"32,611","Continent":"Europe"},"Singapore":{"Total Cases":"26,098","New Cases":"+752","Total Deaths":"21 ","New Deaths":0,"Total Recovered":"4,809","Active Cases":"21,268","Serious\/Critical":"20","Tot Cases\/ 1M pop":"4,461","Deaths\/ 1M pop":"4","Total Tests":"224,262","Tests\/  1M pop ":"38,333","Continent":"Asia"},"Ireland":{"Total Cases":"23,827","New Cases":"+426","Total Deaths":"1,506 ","New Deaths":"+9","Total Recovered":"19,470","Active Cases":"2,851","Serious\/Critical":"69","Tot Cases\/ 1M pop":"4,825","Deaths\/ 1M pop":"305","Total Tests":"258,808","Tests\/  1M pop ":"52,414","Continent":"Europe"},"UAE":{"Total Cases":"21,084","New Cases":"+698","Total Deaths":"208 ","New Deaths":"+2","Total Recovered":"6,930","Active Cases":"13,946","Serious\/Critical":"1","Tot Cases\/ 1M pop":"2,132","Deaths\/ 1M pop":"21","Total Tests":"1,560,923","Tests\/  1M pop ":"157,822","Continent":"Asia"},"Bangladesh":{"Total Cases":"18,863","New Cases":"+1,041","Total Deaths":"283 ","New Deaths":"+14","Total Recovered":"3,361","Active Cases":"15,219","Serious\/Critical":"1","Tot Cases\/ 1M pop":"115","Deaths\/ 1M pop":"2","Total Tests":"151,930","Tests\/  1M pop ":"923","Continent":"Asia"},"Poland":{"Total Cases":"17,615","New Cases":"+411","Total Deaths":"883 ","New Deaths":"+22","Total Recovered":"6,696","Active Cases":"10,036","Serious\/Critical":"160","Tot Cases\/ 1M pop":"465","Deaths\/ 1M pop":"23","Total Tests":"554,357","Tests\/  1M pop ":"14,647","Continent":"Europe"},"Ukraine":{"Total Cases":"16,847","New Cases":"+422","Total Deaths":"456 ","New Deaths":"+17","Total Recovered":"4,143","Active Cases":"12,248","Serious\/Critical":"222","Tot Cases\/ 1M pop":"385","Deaths\/ 1M pop":"10","Total Tests":"202,495","Tests\/  1M pop ":"4,630","Continent":"Europe"},"Israel":{"Total Cases":"16,579","New Cases":"+31","Total Deaths":"265 ","New Deaths":"+1","Total Recovered":"12,521","Active Cases":"3,793","Serious\/Critical":"62","Tot Cases\/ 1M pop":"1,915","Deaths\/ 1M pop":"31","Total Tests":"485,922","Tests\/  1M pop ":"56,140","Continent":"Asia"},"Romania":{"Total Cases":"16,247","New Cases":"+245","Total Deaths":"1,053 ","New Deaths":"+17","Total Recovered":"9,053","Active Cases":"6,141","Serious\/Critical":"225","Tot Cases\/ 1M pop":"845","Deaths\/ 1M pop":"55","Total Tests":"286,217","Tests\/  1M pop ":"14,878","Continent":"Europe"},"Austria":{"Total Cases":"16,058","New Cases":"+61","Total Deaths":"626  ","New Deaths":"+2","Total Recovered":"14,405","Active Cases":"1,027","Serious\/Critical":"54","Tot Cases\/ 1M pop":"1,783","Deaths\/ 1M pop":"70","Total Tests":"344,606","Tests\/  1M pop ":"38,262","Continent":"Europe"},"Japan":{"Total Cases":"16,049","New Cases":0,"Total Deaths":"678 ","New Deaths":0,"Total Recovered":"8,920","Active Cases":"6,451","Serious\/Critical":"243","Tot Cases\/ 1M pop":"127","Deaths\/ 1M pop":"5","Total Tests":"223,667","Tests\/  1M pop ":"1,768","Continent":"Asia"},"Indonesia":{"Total Cases":"16,006","New Cases":"+568","Total Deaths":"1,043 ","New Deaths":"+15","Total Recovered":"3,518","Active Cases":"11,445","Serious\/Critical":0,"Tot Cases\/ 1M pop":"59","Deaths\/ 1M pop":"4","Total Tests":"173,690","Tests\/  1M pop ":"635","Continent":"Asia"},"Colombia":{"Total Cases":"12,930","New Cases":0,"Total Deaths":"509 ","New Deaths":0,"Total Recovered":"3,133","Active Cases":"9,288","Serious\/Critical":"130","Tot Cases\/ 1M pop":"254","Deaths\/ 1M pop":"10","Total Tests":"165,738","Tests\/  1M pop ":"3,257","Continent":"South America"},"South Africa":{"Total Cases":"12,739","New Cases":"+665","Total Deaths":"238 ","New Deaths":"+19","Total Recovered":"5,676","Active Cases":"6,825","Serious\/Critical":"119","Tot Cases\/ 1M pop":"215","Deaths\/ 1M pop":"4","Total Tests":"403,018","Tests\/  1M pop ":"6,795","Continent":"Africa"},"Kuwait":{"Total Cases":"11,975","New Cases":"+947","Total Deaths":"88 ","New Deaths":"+6","Total Recovered":"3,451","Active Cases":"8,436","Serious\/Critical":"175","Tot Cases\/ 1M pop":"2,804","Deaths\/ 1M pop":"21","Total Tests":"231,930","Tests\/  1M pop ":"54,309","Continent":"Asia"},"Philippines":{"Total Cases":"11,876","New Cases":"+258","Total Deaths":"790 ","New Deaths":"+18","Total Recovered":"2,337","Active Cases":"8,749","Serious\/Critical":"77","Tot Cases\/ 1M pop":"108","Deaths\/ 1M pop":"7","Total Tests":"189,469","Tests\/  1M pop ":"1,729","Continent":"Asia"},"Dominican Republic":{"Total Cases":"11,320","New Cases":"+124","Total Deaths":"422 ","New Deaths":"+13","Total Recovered":"3,351","Active Cases":"7,547","Serious\/Critical":"131","Tot Cases\/ 1M pop":"1,044","Deaths\/ 1M pop":"39","Total Tests":"47,774","Tests\/  1M pop ":"4,404","Continent":"North America"},"S. Korea":{"Total Cases":"10,991","New Cases":"+29","Total Deaths":"260 ","New Deaths":"+1","Total Recovered":"9,762","Active Cases":"969","Serious\/Critical":"55","Tot Cases\/ 1M pop":"214","Deaths\/ 1M pop":"5","Total Tests":"711,484","Tests\/  1M pop ":"13,877","Continent":"Asia"},"Egypt":{"Total Cases":"10,829","New Cases":"+398","Total Deaths":"571 ","New Deaths":"+15","Total Recovered":"2,626","Active Cases":"7,632","Serious\/Critical":"41","Tot Cases\/ 1M pop":"106","Deaths\/ 1M pop":"6","Total Tests":"105,000","Tests\/  1M pop ":"1,026","Continent":"Africa"},"Denmark":{"Total Cases":"10,713","New Cases":"+46","Total Deaths":"537 ","New Deaths":"+4","Total Recovered":"8,805","Active Cases":"1,371","Serious\/Critical":"35","Tot Cases\/ 1M pop":"1,850","Deaths\/ 1M pop":"93","Total Tests":"357,986","Tests\/  1M pop ":"61,805","Continent":"Europe"},"Serbia":{"Total Cases":"10,374","New Cases":"+79","Total Deaths":"224 ","New Deaths":"+2","Total Recovered":"4,084","Active Cases":"6,066","Serious\/Critical":"22","Tot Cases\/ 1M pop":"1,187","Deaths\/ 1M pop":"26","Total Tests":"162,797","Tests\/  1M pop ":"18,632","Continent":"Europe"},"Panama":{"Total Cases":"8,944","New Cases":"+161","Total Deaths":"256 ","New Deaths":"+4","Total Recovered":"6,067","Active Cases":"2,621","Serious\/Critical":"87","Tot Cases\/ 1M pop":"2,073","Deaths\/ 1M pop":"59","Total Tests":"45,873","Tests\/  1M pop ":"10,632","Continent":"North America"},"Czechia":{"Total Cases":"8,330","New Cases":"+61","Total Deaths":"292 ","New Deaths":"+2","Total Recovered":"5,227","Active Cases":"2,811","Serious\/Critical":"42","Tot Cases\/ 1M pop":"778","Deaths\/ 1M pop":"27","Total Tests":"334,714","Tests\/  1M pop ":"31,255","Continent":"Europe"},"Norway":{"Total Cases":"8,187","New Cases":"+12","Total Deaths":"232 ","New Deaths":"+3","Total Recovered":"32","Active Cases":"7,923","Serious\/Critical":"23","Tot Cases\/ 1M pop":"1,510","Deaths\/ 1M pop":"43","Total Tests":"212,655","Tests\/  1M pop ":"39,226","Continent":"Europe"},"Australia":{"Total Cases":"6,989","New Cases":"+9","Total Deaths":"98 ","New Deaths":0,"Total Recovered":"6,301","Active Cases":"590","Serious\/Critical":"18","Tot Cases\/ 1M pop":"274","Deaths\/ 1M pop":"4","Total Tests":"943,480","Tests\/  1M pop ":"36,999","Continent":"Australia\/Oceania"},"Argentina":{"Total Cases":"6,879","New Cases":0,"Total Deaths":"344 ","New Deaths":"+15","Total Recovered":"2,385","Active Cases":"4,150","Serious\/Critical":"170","Tot Cases\/ 1M pop":"152","Deaths\/ 1M pop":"8","Total Tests":"93,673","Tests\/  1M pop ":"2,073","Continent":"South America"},"Malaysia":{"Total Cases":"6,819","New Cases":"+40","Total Deaths":"112 ","New Deaths":"+1","Total Recovered":"5,351","Active Cases":"1,356","Serious\/Critical":"16","Tot Cases\/ 1M pop":"211","Deaths\/ 1M pop":"3","Total Tests":"271,721","Tests\/  1M pop ":"8,395","Continent":"Asia"},"Morocco":{"Total Cases":"6,607","New Cases":"+95","Total Deaths":"190 ","New Deaths":"+2","Total Recovered":"3,310","Active Cases":"3,107","Serious\/Critical":"1","Tot Cases\/ 1M pop":"179","Deaths\/ 1M pop":"5","Total Tests":"77,922","Tests\/  1M pop ":"2,111","Continent":"Africa"},"Algeria":{"Total Cases":"6,442","New Cases":"+189","Total Deaths":"529 ","New Deaths":"+7","Total Recovered":"3,158","Active Cases":"2,755","Serious\/Critical":"22","Tot Cases\/ 1M pop":"147","Deaths\/ 1M pop":"12","Total Tests":"6,500","Tests\/  1M pop ":"148","Continent":"Africa"},"Finland":{"Total Cases":"6,145","New Cases":"+91","Total Deaths":"287 ","New Deaths":"+3","Total Recovered":"4,300","Active Cases":"1,558","Serious\/Critical":"33","Tot Cases\/ 1M pop":"1,109","Deaths\/ 1M pop":"52","Total Tests":"137,000","Tests\/  1M pop ":"24,726","Continent":"Europe"},"Bahrain":{"Total Cases":"6,069","New Cases":"+253","Total Deaths":"10 ","New Deaths":0,"Total Recovered":"2,220","Active Cases":"3,839","Serious\/Critical":"6","Tot Cases\/ 1M pop":"3,567","Deaths\/ 1M pop":"6","Total Tests":"205,570","Tests\/  1M pop ":"120,812","Continent":"Asia"},"Afghanistan":{"Total Cases":"5,639","New Cases":"+413","Total Deaths":"136 ","New Deaths":"+4","Total Recovered":"691","Active Cases":"4,812","Serious\/Critical":"7","Tot Cases\/ 1M pop":"145","Deaths\/ 1M pop":"3","Total Tests":"19,732","Tests\/  1M pop ":"507","Continent":"Asia"},"Kazakhstan":{"Total Cases":"5,571","New Cases":"+154","Total Deaths":"32 ","New Deaths":0,"Total Recovered":"2,531","Active Cases":"3,008","Serious\/Critical":"31","Tot Cases\/ 1M pop":"297","Deaths\/ 1M pop":"2","Total Tests":"459,736","Tests\/  1M pop ":"24,484","Continent":"Asia"},"Moldova":{"Total Cases":"5,553","New Cases":"+147","Total Deaths":"194 ","New Deaths":"+9","Total Recovered":"2,228","Active Cases":"3,131","Serious\/Critical":"251","Tot Cases\/ 1M pop":"1,377","Deaths\/ 1M pop":"48","Total Tests":"20,447","Tests\/  1M pop ":"5,069","Continent":"Europe"},"Ghana":{"Total Cases":"5,408","New Cases":0,"Total Deaths":"24 ","New Deaths":0,"Total Recovered":"514","Active Cases":"4,870","Serious\/Critical":"5","Tot Cases\/ 1M pop":"174","Deaths\/ 1M pop":"0.8","Total Tests":"164,452","Tests\/  1M pop ":"5,292","Continent":"Africa"},"Nigeria":{"Total Cases":"4,971","New Cases":0,"Total Deaths":"164 ","New Deaths":0,"Total Recovered":"1,070","Active Cases":"3,737","Serious\/Critical":"7","Tot Cases\/ 1M pop":"24","Deaths\/ 1M pop":"0.8","Total Tests":"29,408","Tests\/  1M pop ":"143","Continent":"Africa"},"Oman":{"Total Cases":"4,341","New Cases":"+322","Total Deaths":"18 ","New Deaths":"+1","Total Recovered":"1,303","Active Cases":"3,020","Serious\/Critical":"31","Tot Cases\/ 1M pop":"850","Deaths\/ 1M pop":"4","Total Tests":"61,000","Tests\/  1M pop ":"11,945","Continent":"Asia"},"Luxembourg":{"Total Cases":"3,915","New Cases":"+11","Total Deaths":"103 ","New Deaths":0,"Total Recovered":"3,665","Active Cases":"147","Serious\/Critical":"11","Tot Cases\/ 1M pop":"6,254","Deaths\/ 1M pop":"165","Total Tests":"58,727","Tests\/  1M pop ":"93,816","Continent":"Europe"},"Armenia":{"Total Cases":"3,860","New Cases":"+142","Total Deaths":"49 ","New Deaths":"+1","Total Recovered":"1,572","Active Cases":"2,239","Serious\/Critical":"10","Tot Cases\/ 1M pop":"1,303","Deaths\/ 1M pop":"17","Total Tests":"36,016","Tests\/  1M pop ":"12,154","Continent":"Asia"},"Hungary":{"Total Cases":"3,380","New Cases":"+39","Total Deaths":"436 ","New Deaths":"+6","Total Recovered":"1,169","Active Cases":"1,775","Serious\/Critical":"49","Tot Cases\/ 1M pop":"350","Deaths\/ 1M pop":"45","Total Tests":"123,258","Tests\/  1M pop ":"12,759","Continent":"Europe"},"Bolivia":{"Total Cases":"3,148","New Cases":"+184","Total Deaths":"142  ","New Deaths":"+14","Total Recovered":"339","Active Cases":"2,667","Serious\/Critical":"3","Tot Cases\/ 1M pop":"270","Deaths\/ 1M pop":"12","Total Tests":"7,651","Tests\/  1M pop ":"655","Continent":"South America"},"Iraq":{"Total Cases":"3,143","New Cases":"+111","Total Deaths":"115 ","New Deaths":0,"Total Recovered":"2,028","Active Cases":"1,000","Serious\/Critical":0,"Tot Cases\/ 1M pop":"78","Deaths\/ 1M pop":"3","Total Tests":"140,573","Tests\/  1M pop ":"3,495","Continent":"Asia"},"Thailand":{"Total Cases":"3,018","New Cases":"+1","Total Deaths":"56 ","New Deaths":0,"Total Recovered":"2,850","Active Cases":"112","Serious\/Critical":"61","Tot Cases\/ 1M pop":"43","Deaths\/ 1M pop":"0.8","Total Tests":"286,008","Tests\/  1M pop ":"4,098","Continent":"Asia"},"Cameroon":{"Total Cases":"2,954","New Cases":"+154","Total Deaths":"139 ","New Deaths":"+3","Total Recovered":"1,553","Active Cases":"1,262","Serious\/Critical":"28","Tot Cases\/ 1M pop":"111","Deaths\/ 1M pop":"5","Total Tests":0,"Tests\/  1M pop ":0,"Continent":"Africa"},"Azerbaijan":{"Total Cases":"2,879","New Cases":"+121","Total Deaths":"35 ","New Deaths":0,"Total Recovered":"1,833","Active Cases":"1,011","Serious\/Critical":"29","Tot Cases\/ 1M pop":"284","Deaths\/ 1M pop":"3","Total Tests":"214,291","Tests\/  1M pop ":"21,135","Continent":"Asia"},"Greece":{"Total Cases":"2,770","New Cases":"+10","Total Deaths":"156 ","New Deaths":"+1","Total Recovered":"1,374","Active Cases":"1,240","Serious\/Critical":"24","Tot Cases\/ 1M pop":"266","Deaths\/ 1M pop":"15","Total Tests":"116,233","Tests\/  1M pop ":"11,152","Continent":"Europe"},"Uzbekistan":{"Total Cases":"2,636","New Cases":"+24","Total Deaths":"11 ","New Deaths":0,"Total Recovered":"2,136","Active Cases":"489","Serious\/Critical":"8","Tot Cases\/ 1M pop":"79","Deaths\/ 1M pop":"0.3","Total Tests":"325,000","Tests\/  1M pop ":"9,710","Continent":"Asia"},"Guinea":{"Total Cases":"2,374","New Cases":0,"Total Deaths":"14 ","New Deaths":0,"Total Recovered":"856","Active Cases":"1,504","Serious\/Critical":0,"Tot Cases\/ 1M pop":"181","Deaths\/ 1M pop":"1","Total Tests":0,"Tests\/  1M pop ":0,"Continent":"Africa"},"Honduras":{"Total Cases":"2,255","New Cases":"+175","Total Deaths":"123 ","New Deaths":"+2","Total Recovered":"237","Active Cases":"1,895","Serious\/Critical":"10","Tot Cases\/ 1M pop":"228","Deaths\/ 1M pop":"12","Total Tests":"5,653","Tests\/  1M pop ":"571","Continent":"North America"},"Croatia":{"Total Cases":"2,221","New Cases":"+8","Total Deaths":"94 ","New Deaths":0,"Total Recovered":"1,850","Active Cases":"277","Serious\/Critical":"7","Tot Cases\/ 1M pop":"541","Deaths\/ 1M pop":"23","Total Tests":"50,340","Tests\/  1M pop ":"12,262","Continent":"Europe"},"Bosnia and Herzegovina":{"Total Cases":"2,218","New Cases":"+37","Total Deaths":"122 ","New Deaths":"+2","Total Recovered":"1,272","Active Cases":"824","Serious\/Critical":"4","Tot Cases\/ 1M pop":"676","Deaths\/ 1M pop":"37","Total Tests":"45,810","Tests\/  1M pop ":"13,963","Continent":"Europe"},"Senegal":{"Total Cases":"2,189","New Cases":"+84","Total Deaths":"23 ","New Deaths":"+2","Total Recovered":"842","Active Cases":"1,324","Serious\/Critical":"6","Tot Cases\/ 1M pop":"131","Deaths\/ 1M pop":"1","Total Tests":"24,599","Tests\/  1M pop ":"1,469","Continent":"Africa"},"Bulgaria":{"Total Cases":"2,100","New Cases":"+31","Total Deaths":"99 ","New Deaths":"+3","Total Recovered":"531","Active Cases":"1,470","Serious\/Critical":"51","Tot Cases\/ 1M pop":"302","Deaths\/ 1M pop":"14","Total Tests":"61,711","Tests\/  1M pop ":"8,881","Continent":"Europe"},"Ivory Coast":{"Total Cases":"1,912","New Cases":0,"Total Deaths":"24 ","New Deaths":0,"Total Recovered":"902","Active Cases":"986","Serious\/Critical":0,"Tot Cases\/ 1M pop":"72","Deaths\/ 1M pop":"0.9","Total Tests":"15,260","Tests\/  1M pop ":"579","Continent":"Africa"},"Cuba":{"Total Cases":"1,830","New Cases":"+20","Total Deaths":"79 ","New Deaths":0,"Total Recovered":"1,383","Active Cases":"368","Serious\/Critical":"9","Tot Cases\/ 1M pop":"162","Deaths\/ 1M pop":"7","Total Tests":"75,142","Tests\/  1M pop ":"6,634","Continent":"North America"},"Sudan":{"Total Cases":"1,818","New Cases":0,"Total Deaths":"90 ","New Deaths":0,"Total Recovered":"198","Active Cases":"1,530","Serious\/Critical":0,"Tot Cases\/ 1M pop":"41","Deaths\/ 1M pop":"2","Total Tests":0,"Tests\/  1M pop ":0,"Continent":"Africa"},"Iceland":{"Total Cases":"1,802","New Cases":0,"Total Deaths":"10 ","New Deaths":0,"Total Recovered":"1,780","Active Cases":"12","Serious\/Critical":0,"Tot Cases\/ 1M pop":"5,281","Deaths\/ 1M pop":"29","Total Tests":"55,626","Tests\/  1M pop ":"163,010","Continent":"Europe"},"Estonia":{"Total Cases":"1,758","New Cases":"+7","Total Deaths":"62 ","New Deaths":"+1","Total Recovered":"909","Active Cases":"787","Serious\/Critical":"5","Tot Cases\/ 1M pop":"1,325","Deaths\/ 1M pop":"47","Total Tests":"67,130","Tests\/  1M pop ":"50,606","Continent":"Europe"},"North Macedonia":{"Total Cases":"1,723","New Cases":"+29","Total Deaths":"95 ","New Deaths":0,"Total Recovered":"1,235","Active Cases":"393","Serious\/Critical":"21","Tot Cases\/ 1M pop":"827","Deaths\/ 1M pop":"46","Total Tests":"20,088","Tests\/  1M pop ":"9,642","Continent":"Europe"},"Lithuania":{"Total Cases":"1,511","New Cases":"+6","Total Deaths":"54 ","New Deaths":0,"Total Recovered":"934","Active Cases":"523","Serious\/Critical":"17","Tot Cases\/ 1M pop":"555","Deaths\/ 1M pop":"20","Total Tests":"208,253","Tests\/  1M pop ":"76,499","Continent":"Europe"},"New Zealand":{"Total Cases":"1,497","New Cases":0,"Total Deaths":"21 ","New Deaths":0,"Total Recovered":"1,411","Active Cases":"65","Serious\/Critical":"2","Tot Cases\/ 1M pop":"310","Deaths\/ 1M pop":"4","Total Tests":"209,613","Tests\/  1M pop ":"43,468","Continent":"Australia\/Oceania"},"Slovakia":{"Total Cases":"1,477","New Cases":"+8","Total Deaths":"27 ","New Deaths":0,"Total Recovered":"1,112","Active Cases":"338","Serious\/Critical":"5","Tot Cases\/ 1M pop":"271","Deaths\/ 1M pop":"5","Total Tests":"131,910","Tests\/  1M pop ":"24,161","Continent":"Europe"},"Slovenia":{"Total Cases":"1,464","New Cases":"+1","Total Deaths":"103 ","New Deaths":0,"Total Recovered":"267","Active Cases":"1,094","Serious\/Critical":"7","Tot Cases\/ 1M pop":"704","Deaths\/ 1M pop":"50","Total Tests":"66,678","Tests\/  1M pop ":"32,073","Continent":"Europe"},"Guatemala":{"Total Cases":"1,342","New Cases":"+143","Total Deaths":"29 ","New Deaths":"+2","Total Recovered":"121","Active Cases":"1,192","Serious\/Critical":"5","Tot Cases\/ 1M pop":"75","Deaths\/ 1M pop":"2","Total Tests":"7,200","Tests\/  1M pop ":"402","Continent":"North America"},"Djibouti":{"Total Cases":"1,284","New Cases":"+16","Total Deaths":"3 ","New Deaths":0,"Total Recovered":"905","Active Cases":"376","Serious\/Critical":0,"Tot Cases\/ 1M pop":"1,300","Deaths\/ 1M pop":"3","Total Tests":"16,647","Tests\/  1M pop ":"16,849","Continent":"Africa"},"DRC":{"Total Cases":"1,242","New Cases":"+73","Total Deaths":"50 ","New Deaths":0,"Total Recovered":"157","Active Cases":"1,035","Serious\/Critical":0,"Tot Cases\/ 1M pop":"14","Deaths\/ 1M pop":"0.6","Total Tests":0,"Tests\/  1M pop ":0,"Continent":"Africa"},"Somalia":{"Total Cases":"1,219","New Cases":0,"Total Deaths":"52 ","New Deaths":0,"Total Recovered":"130","Active Cases":"1,037","Serious\/Critical":"2","Tot Cases\/ 1M pop":"77","Deaths\/ 1M pop":"3","Total Tests":0,"Tests\/  1M pop ":0,"Continent":"Africa"},"Mayotte":{"Total Cases":"1,143","New Cases":0,"Total Deaths":"14 ","New Deaths":0,"Total Recovered":"627","Active Cases":"502","Serious\/Critical":"6","Tot Cases\/ 1M pop":"4,190","Deaths\/ 1M pop":"51","Total Tests":"4,800","Tests\/  1M pop ":"17,594","Continent":"Africa"},"El Salvador":{"Total Cases":"1,112","New Cases":"+75","Total Deaths":"20 ","New Deaths":0,"Total Recovered":"405","Active Cases":"687","Serious\/Critical":"19","Tot Cases\/ 1M pop":"171","Deaths\/ 1M pop":"3","Total Tests":"48,913","Tests\/  1M pop ":"7,541","Continent":"North America"},"Kyrgyzstan":{"Total Cases":"1,082","New Cases":"+38","Total Deaths":"12 ","New Deaths":0,"Total Recovered":"735","Active Cases":"335","Serious\/Critical":"13","Tot Cases\/ 1M pop":"166","Deaths\/ 1M pop":"2","Total Tests":"59,490","Tests\/  1M pop ":"9,118","Continent":"Asia"},"Hong Kong":{"Total Cases":"1,052","New Cases":"+1","Total Deaths":"4 ","New Deaths":0,"Total Recovered":"1,009","Active Cases":"39","Serious\/Critical":"1","Tot Cases\/ 1M pop":"140","Deaths\/ 1M pop":"0.5","Total Tests":"168,291","Tests\/  1M pop ":"22,448","Continent":"Asia"},"Tunisia":{"Total Cases":"1,032","New Cases":0,"Total Deaths":"45 ","New Deaths":0,"Total Recovered":"759","Active Cases":"228","Serious\/Critical":"5","Tot Cases\/ 1M pop":"87","Deaths\/ 1M pop":"4","Total Tests":"34,323","Tests\/  1M pop ":"2,904","Continent":"Africa"},"Gabon":{"Total Cases":"1,004","New Cases":0,"Total Deaths":"9 ","New Deaths":0,"Total Recovered":"152","Active Cases":"843","Serious\/Critical":"1","Tot Cases\/ 1M pop":"451","Deaths\/ 1M pop":"4","Total Tests":"5,530","Tests\/  1M pop ":"2,485","Continent":"Africa"},"Maldives":{"Total Cases":"968","New Cases":"+13","Total Deaths":"4 ","New Deaths":0,"Total Recovered":"40","Active Cases":"924","Serious\/Critical":"2","Tot Cases\/ 1M pop":"1,791","Deaths\/ 1M pop":"7","Total Tests":"11,775","Tests\/  1M pop ":"21,784","Continent":"Asia"},"Latvia":{"Total Cases":"962","New Cases":"+11","Total Deaths":"19 ","New Deaths":0,"Total Recovered":"627","Active Cases":"316","Serious\/Critical":"2","Tot Cases\/ 1M pop":"510","Deaths\/ 1M pop":"10","Total Tests":"83,275","Tests\/  1M pop ":"44,150","Continent":"Europe"},"Sri Lanka":{"Total Cases":"925","New Cases":"+32","Total Deaths":"9 ","New Deaths":0,"Total Recovered":"445","Active Cases":"471","Serious\/Critical":"1","Tot Cases\/ 1M pop":"43","Deaths\/ 1M pop":"0.4","Total Tests":"39,629","Tests\/  1M pop ":"1,851","Continent":"Asia"},"Tajikistan":{"Total Cases":"907","New Cases":"+106","Total Deaths":"29 ","New Deaths":"+6","Total Recovered":0,"Active Cases":"878","Serious\/Critical":0,"Tot Cases\/ 1M pop":"95","Deaths\/ 1M pop":"3","Total Tests":0,"Tests\/  1M pop ":0,"Continent":"Asia"},"Cyprus":{"Total Cases":"907","New Cases":"+2","Total Deaths":"17 ","New Deaths":0,"Total Recovered":"481","Active Cases":"409","Serious\/Critical":"10","Tot Cases\/ 1M pop":"751","Deaths\/ 1M pop":"14","Total Tests":"81,942","Tests\/  1M pop ":"67,869","Continent":"Asia"},"Albania":{"Total Cases":"898","New Cases":"+18","Total Deaths":"31 ","New Deaths":0,"Total Recovered":"694","Active Cases":"173","Serious\/Critical":"1","Tot Cases\/ 1M pop":"312","Deaths\/ 1M pop":"11","Total Tests":"11,239","Tests\/  1M pop ":"3,905","Continent":"Europe"},"Lebanon":{"Total Cases":"886","New Cases":"+8","Total Deaths":"26 ","New Deaths":0,"Total Recovered":"236","Active Cases":"624","Serious\/Critical":"4","Tot Cases\/ 1M pop":"130","Deaths\/ 1M pop":"4","Total Tests":"56,385","Tests\/  1M pop ":"8,261","Continent":"Asia"},"Niger":{"Total Cases":"860","New Cases":0,"Total Deaths":"49 ","New Deaths":0,"Total Recovered":"658","Active Cases":"153","Serious\/Critical":0,"Tot Cases\/ 1M pop":"36","Deaths\/ 1M pop":"2","Total Tests":"5,691","Tests\/  1M pop ":"235","Continent":"Africa"},"Guinea-Bissau":{"Total Cases":"836","New Cases":0,"Total Deaths":"3 ","New Deaths":0,"Total Recovered":"26","Active Cases":"807","Serious\/Critical":0,"Tot Cases\/ 1M pop":"425","Deaths\/ 1M pop":"2","Total Tests":"1,500","Tests\/  1M pop ":"762","Continent":"Africa"},"Costa Rica":{"Total Cases":"830","New Cases":"+15","Total Deaths":"8 ","New Deaths":"+1","Total Recovered":"535","Active Cases":"287","Serious\/Critical":"4","Tot Cases\/ 1M pop":"163","Deaths\/ 1M pop":"2","Total Tests":"18,388","Tests\/  1M pop ":"3,610","Continent":"North America"},"Mali":{"Total Cases":"779","New Cases":"+21","Total Deaths":"46 ","New Deaths":"+2","Total Recovered":"436","Active Cases":"297","Serious\/Critical":0,"Tot Cases\/ 1M pop":"38","Deaths\/ 1M pop":"2","Total Tests":"2,498","Tests\/  1M pop ":"123","Continent":"Africa"},"Burkina Faso":{"Total Cases":"773","New Cases":0,"Total Deaths":"51 ","New Deaths":0,"Total Recovered":"592","Active Cases":"130","Serious\/Critical":0,"Tot Cases\/ 1M pop":"37","Deaths\/ 1M pop":"2","Total Tests":0,"Tests\/  1M pop ":0,"Continent":"Africa"},"Andorra":{"Total Cases":"761","New Cases":"+1","Total Deaths":"49 ","New Deaths":0,"Total Recovered":"596","Active Cases":"116","Serious\/Critical":"3","Tot Cases\/ 1M pop":"9,849","Deaths\/ 1M pop":"634","Total Tests":"1,673","Tests\/  1M pop ":"21,653","Continent":"Europe"},"Kenya":{"Total Cases":"758","New Cases":"+21","Total Deaths":"42 ","New Deaths":"+2","Total Recovered":"284","Active Cases":"432","Serious\/Critical":"1","Tot Cases\/ 1M pop":"14","Deaths\/ 1M pop":"0.8","Total Tests":"36,918","Tests\/  1M pop ":"687","Continent":"Africa"},"Paraguay":{"Total Cases":"754","New Cases":"+14","Total Deaths":"11 ","New Deaths":0,"Total Recovered":"184","Active Cases":"559","Serious\/Critical":0,"Tot Cases\/ 1M pop":"106","Deaths\/ 1M pop":"2","Total Tests":"18,184","Tests\/  1M pop ":"2,549","Continent":"South America"},"Uruguay":{"Total Cases":"719","New Cases":0,"Total Deaths":"19 ","New Deaths":0,"Total Recovered":"545","Active Cases":"155","Serious\/Critical":"8","Tot Cases\/ 1M pop":"207","Deaths\/ 1M pop":"5","Total Tests":"30,209","Tests\/  1M pop ":"8,696","Continent":"South America"},"Diamond Princess":{"Total Cases":"712","New Cases":0,"Total Deaths":"13 ","New Deaths":0,"Total Recovered":"651","Active Cases":"48","Serious\/Critical":"4","Tot Cases\/ 1M pop":0,"Deaths\/ 1M pop":0,"Total Tests":0,"Tests\/  1M pop ":0,"Continent":0},"Georgia":{"Total Cases":"667","New Cases":"+20","Total Deaths":"12  ","New Deaths":"+1","Total Recovered":"383","Active Cases":"272","Serious\/Critical":"6","Tot Cases\/ 1M pop":"167","Deaths\/ 1M pop":"3","Total Tests":"34,500","Tests\/  1M pop ":"8,648","Continent":"Asia"},"Zambia":{"Total Cases":"654","New Cases":"+208","Total Deaths":"7 ","New Deaths":0,"Total Recovered":"124","Active Cases":"523","Serious\/Critical":"1","Tot Cases\/ 1M pop":"36","Deaths\/ 1M pop":"0.4","Total Tests":"15,487","Tests\/  1M pop ":"842","Continent":"Africa"},"San Marino":{"Total Cases":"648","New Cases":"+5","Total Deaths":"41 ","New Deaths":0,"Total Recovered":"172","Active Cases":"435","Serious\/Critical":"1","Tot Cases\/ 1M pop":"19,098","Deaths\/ 1M pop":"1,208","Total Tests":"3,300","Tests\/  1M pop ":"97,256","Continent":"Europe"},"Jordan":{"Total Cases":"586","New Cases":"+4","Total Deaths":"9 ","New Deaths":0,"Total Recovered":"393","Active Cases":"184","Serious\/Critical":"5","Tot Cases\/ 1M pop":"57","Deaths\/ 1M pop":"0.9","Total Tests":"131,985","Tests\/  1M pop ":"12,936","Continent":"Asia"},"Channel Islands":{"Total Cases":"548","New Cases":0,"Total Deaths":"43 ","New Deaths":0,"Total Recovered":"456","Active Cases":"49","Serious\/Critical":0,"Tot Cases\/ 1M pop":"3,152","Deaths\/ 1M pop":"247","Total Tests":"5,342","Tests\/  1M pop ":"30,725","Continent":"Europe"},"Equatorial Guinea":{"Total Cases":"522","New Cases":0,"Total Deaths":"6 ","New Deaths":0,"Total Recovered":"13","Active Cases":"503","Serious\/Critical":0,"Tot Cases\/ 1M pop":"372","Deaths\/ 1M pop":"4","Total Tests":"854","Tests\/  1M pop ":"609","Continent":"Africa"},"Malta":{"Total Cases":"522","New Cases":"+14","Total Deaths":"6 ","New Deaths":0,"Total Recovered":"443","Active Cases":"73","Serious\/Critical":"1","Tot Cases\/ 1M pop":"1,182","Deaths\/ 1M pop":"14","Total Tests":"45,967","Tests\/  1M pop ":"104,105","Continent":"Europe"},"Tanzania":{"Total Cases":"509","New Cases":0,"Total Deaths":"21 ","New Deaths":0,"Total Recovered":"183","Active Cases":"305","Serious\/Critical":"7","Tot Cases\/ 1M pop":"9","Deaths\/ 1M pop":"0.4","Total Tests":0,"Tests\/  1M pop ":0,"Continent":"Africa"},"Jamaica":{"Total Cases":"509","New Cases":"+2","Total Deaths":"9 ","New Deaths":0,"Total Recovered":"113","Active Cases":"387","Serious\/Critical":0,"Tot Cases\/ 1M pop":"172","Deaths\/ 1M pop":"3","Total Tests":"7,552","Tests\/  1M pop ":"2,550","Continent":"North America"},"Venezuela":{"Total Cases":"440","New Cases":0,"Total Deaths":"10 ","New Deaths":0,"Total Recovered":"220","Active Cases":"210","Serious\/Critical":"2","Tot Cases\/ 1M pop":"15","Deaths\/ 1M pop":"0.4","Total Tests":"525,902","Tests\/  1M pop ":"18,494","Continent":"South America"},"Taiwan":{"Total Cases":"440","New Cases":0,"Total Deaths":"7 ","New Deaths":0,"Total Recovered":"383","Active Cases":"50","Serious\/Critical":0,"Tot Cases\/ 1M pop":"18","Deaths\/ 1M pop":"0.3","Total Tests":"68,335","Tests\/  1M pop ":"2,869","Continent":"Asia"},"R\u00e9union":{"Total Cases":"439","New Cases":0,"Total Deaths":" ","New Deaths":0,"Total Recovered":"354","Active Cases":"85","Serious\/Critical":"4","Tot Cases\/ 1M pop":"490","Deaths\/ 1M pop":0,"Total Tests":"17,200","Tests\/  1M pop ":"19,211","Continent":"Africa"},"Sierra Leone":{"Total Cases":"408","New Cases":"+21","Total Deaths":"26 ","New Deaths":0,"Total Recovered":"97","Active Cases":"285","Serious\/Critical":0,"Tot Cases\/ 1M pop":"51","Deaths\/ 1M pop":"3","Total Tests":0,"Tests\/  1M pop ":0,"Continent":"Africa"},"Chad":{"Total Cases":"399","New Cases":"+27","Total Deaths":"46 ","New Deaths":"+4","Total Recovered":"83","Active Cases":"270","Serious\/Critical":0,"Tot Cases\/ 1M pop":"24","Deaths\/ 1M pop":"3","Total Tests":0,"Tests\/  1M pop ":0,"Continent":"Africa"},"Palestine":{"Total Cases":"375","New Cases":0,"Total Deaths":"2 ","New Deaths":0,"Total Recovered":"310","Active Cases":"63","Serious\/Critical":0,"Tot Cases\/ 1M pop":"74","Deaths\/ 1M pop":"0.4","Total Tests":"43,566","Tests\/  1M pop ":"8,540","Continent":"Asia"},"Benin":{"Total Cases":"339","New Cases":"+12","Total Deaths":"2 ","New Deaths":0,"Total Recovered":"83","Active Cases":"254","Serious\/Critical":0,"Tot Cases\/ 1M pop":"28","Deaths\/ 1M pop":"0.2","Total Tests":"25,471","Tests\/  1M pop ":"2,101","Continent":"Africa"},"Congo":{"Total Cases":"333","New Cases":0,"Total Deaths":"11 ","New Deaths":0,"Total Recovered":"53","Active Cases":"269","Serious\/Critical":0,"Tot Cases\/ 1M pop":"60","Deaths\/ 1M pop":"2","Total Tests":0,"Tests\/  1M pop ":0,"Continent":"Africa"},"Isle of Man":{"Total Cases":"332","New Cases":0,"Total Deaths":"23 ","New Deaths":0,"Total Recovered":"274","Active Cases":"35","Serious\/Critical":"20","Tot Cases\/ 1M pop":"3,904","Deaths\/ 1M pop":"270","Total Tests":"3,973","Tests\/  1M pop ":"46,723","Continent":"Europe"},"Mauritius":{"Total Cases":"332","New Cases":0,"Total Deaths":"10 ","New Deaths":0,"Total Recovered":"322","Active Cases":"0","Serious\/Critical":0,"Tot Cases\/ 1M pop":"261","Deaths\/ 1M pop":"8","Total Tests":"69,773","Tests\/  1M pop ":"54,863","Continent":"Africa"},"Montenegro":{"Total Cases":"324","New Cases":0,"Total Deaths":"9 ","New Deaths":0,"Total Recovered":"309","Active Cases":"6","Serious\/Critical":"2","Tot Cases\/ 1M pop":"516","Deaths\/ 1M pop":"14","Total Tests":"10,167","Tests\/  1M pop ":"16,188","Continent":"Europe"},"Cabo Verde":{"Total Cases":"315","New Cases":"+26","Total Deaths":"2 ","New Deaths":0,"Total Recovered":"67","Active Cases":"246","Serious\/Critical":0,"Tot Cases\/ 1M pop":"567","Deaths\/ 1M pop":"4","Total Tests":"791","Tests\/  1M pop ":"1,423","Continent":"Africa"},"Vietnam":{"Total Cases":"288","New Cases":0,"Total Deaths":" ","New Deaths":0,"Total Recovered":"260","Active Cases":"28","Serious\/Critical":"2","Tot Cases\/ 1M pop":"3","Deaths\/ 1M pop":0,"Total Tests":"275,000","Tests\/  1M pop ":"2,825","Continent":"Asia"},"Rwanda":{"Total Cases":"287","New Cases":0,"Total Deaths":" ","New Deaths":0,"Total Recovered":"168","Active Cases":"119","Serious\/Critical":0,"Tot Cases\/ 1M pop":"22","Deaths\/ 1M pop":0,"Total Tests":"45,140","Tests\/  1M pop ":"3,485","Continent":"Africa"},"Ethiopia":{"Total Cases":"272","New Cases":"+9","Total Deaths":"5 ","New Deaths":0,"Total Recovered":"108","Active Cases":"159","Serious\/Critical":0,"Tot Cases\/ 1M pop":"2","Deaths\/ 1M pop":"0.04","Total Tests":"45,278","Tests\/  1M pop ":"394","Continent":"Africa"},"Nepal":{"Total Cases":"246","New Cases":"+3","Total Deaths":" ","New Deaths":0,"Total Recovered":"35","Active Cases":"211","Serious\/Critical":0,"Tot Cases\/ 1M pop":"8","Deaths\/ 1M pop":0,"Total Tests":"81,685","Tests\/  1M pop ":"2,803","Continent":"Asia"},"Haiti":{"Total Cases":"234","New Cases":"+15","Total Deaths":"18 ","New Deaths":0,"Total Recovered":"17","Active Cases":"199","Serious\/Critical":0,"Tot Cases\/ 1M pop":"21","Deaths\/ 1M pop":"2","Total Tests":"1,408","Tests\/  1M pop ":"123","Continent":"North America"},"Madagascar":{"Total Cases":"230","New Cases":"+18","Total Deaths":" ","New Deaths":0,"Total Recovered":"108","Active Cases":"122","Serious\/Critical":"1","Tot Cases\/ 1M pop":"8","Deaths\/ 1M pop":0,"Total Tests":"5,670","Tests\/  1M pop ":"205","Continent":"Africa"},"Sao Tome and Principe":{"Total Cases":"220","New Cases":0,"Total Deaths":"6 ","New Deaths":0,"Total Recovered":"4","Active Cases":"210","Serious\/Critical":0,"Tot Cases\/ 1M pop":"1,004","Deaths\/ 1M pop":"27","Total Tests":"175","Tests\/  1M pop ":"799","Continent":"Africa"},"Togo":{"Total Cases":"219","New Cases":0,"Total Deaths":"11 ","New Deaths":0,"Total Recovered":"96","Active Cases":"112","Serious\/Critical":0,"Tot Cases\/ 1M pop":"26","Deaths\/ 1M pop":"1","Total Tests":"11,374","Tests\/  1M pop ":"1,374","Continent":"Africa"},"Liberia":{"Total Cases":"215","New Cases":"+2","Total Deaths":"20 ","New Deaths":0,"Total Recovered":"105","Active Cases":"90","Serious\/Critical":0,"Tot Cases\/ 1M pop":"43","Deaths\/ 1M pop":"4","Total Tests":0,"Tests\/  1M pop ":0,"Continent":"Africa"},"South Sudan":{"Total Cases":"203","New Cases":0,"Total Deaths":" ","New Deaths":0,"Total Recovered":"2","Active Cases":"201","Serious\/Critical":0,"Tot Cases\/ 1M pop":"18","Deaths\/ 1M pop":0,"Total Tests":"1,247","Tests\/  1M pop ":"111","Continent":"Africa"},"Martinique":{"Total Cases":"189","New Cases":0,"Total Deaths":"14 ","New Deaths":0,"Total Recovered":"91","Active Cases":"84","Serious\/Critical":"2","Tot Cases\/ 1M pop":"504","Deaths\/ 1M pop":"37","Total Tests":0,"Tests\/  1M pop ":0,"Continent":"North America"},"Eswatini":{"Total Cases":"187","New Cases":0,"Total Deaths":"2 ","New Deaths":0,"Total Recovered":"51","Active Cases":"134","Serious\/Critical":0,"Tot Cases\/ 1M pop":"161","Deaths\/ 1M pop":"2","Total Tests":"2,262","Tests\/  1M pop ":"1,950","Continent":"Africa"},"Faeroe Islands":{"Total Cases":"187","New Cases":0,"Total Deaths":" ","New Deaths":0,"Total Recovered":"187","Active Cases":"0","Serious\/Critical":0,"Tot Cases\/ 1M pop":"3,827","Deaths\/ 1M pop":0,"Total Tests":"8,638","Tests\/  1M pop ":"176,780","Continent":"Europe"},"Myanmar":{"Total Cases":"181","New Cases":0,"Total Deaths":"6 ","New Deaths":0,"Total Recovered":"84","Active Cases":"91","Serious\/Critical":0,"Tot Cases\/ 1M pop":"3","Deaths\/ 1M pop":"0.1","Total Tests":"12,482","Tests\/  1M pop ":"229","Continent":"Asia"},"Guadeloupe":{"Total Cases":"155","New Cases":0,"Total Deaths":"13 ","New Deaths":0,"Total Recovered":"109","Active Cases":"33","Serious\/Critical":"4","Tot Cases\/ 1M pop":"387","Deaths\/ 1M pop":"32","Total Tests":0,"Tests\/  1M pop ":0,"Continent":"North America"},"French Guiana":{"Total Cases":"153","New Cases":0,"Total Deaths":"1 ","New Deaths":0,"Total Recovered":"124","Active Cases":"28","Serious\/Critical":0,"Tot Cases\/ 1M pop":"512","Deaths\/ 1M pop":"3","Total Tests":0,"Tests\/  1M pop ":0,"Continent":"South America"},"Gibraltar":{"Total Cases":"147","New Cases":0,"Total Deaths":" ","New Deaths":0,"Total Recovered":"144","Active Cases":"3","Serious\/Critical":0,"Tot Cases\/ 1M pop":"4,363","Deaths\/ 1M pop":0,"Total Tests":"4,576","Tests\/  1M pop ":"135,823","Continent":"Europe"},"CAR":{"Total Cases":"143","New Cases":0,"Total Deaths":" ","New Deaths":0,"Total Recovered":"10","Active Cases":"133","Serious\/Critical":0,"Tot Cases\/ 1M pop":"30","Deaths\/ 1M pop":0,"Total Tests":"3,498","Tests\/  1M pop ":"724","Continent":"Africa"},"Brunei ":{"Total Cases":"141","New Cases":0,"Total Deaths":"1 ","New Deaths":0,"Total Recovered":"134","Active Cases":"6","Serious\/Critical":"2","Tot Cases\/ 1M pop":"322","Deaths\/ 1M pop":"2","Total Tests":"16,523","Tests\/  1M pop ":"37,769","Continent":"Asia"},"Uganda":{"Total Cases":"139","New Cases":0,"Total Deaths":" ","New Deaths":0,"Total Recovered":"55","Active Cases":"84","Serious\/Critical":0,"Tot Cases\/ 1M pop":"3","Deaths\/ 1M pop":0,"Total Tests":"65,663","Tests\/  1M pop ":"1,436","Continent":"Africa"},"Cambodia":{"Total Cases":"122","New Cases":0,"Total Deaths":" ","New Deaths":0,"Total Recovered":"121","Active Cases":"1","Serious\/Critical":"1","Tot Cases\/ 1M pop":"7","Deaths\/ 1M pop":0,"Total Tests":"14,461","Tests\/  1M pop ":"865","Continent":"Asia"},"Bermuda":{"Total Cases":"121","New Cases":0,"Total Deaths":"8 ","New Deaths":0,"Total Recovered":"66","Active Cases":"47","Serious\/Critical":"2","Tot Cases\/ 1M pop":"1,943","Deaths\/ 1M pop":"128","Total Tests":"4,642","Tests\/  1M pop ":"74,537","Continent":"North America"},"Trinidad and Tobago":{"Total Cases":"116","New Cases":0,"Total Deaths":"8 ","New Deaths":0,"Total Recovered":"107","Active Cases":"1","Serious\/Critical":0,"Tot Cases\/ 1M pop":"83","Deaths\/ 1M pop":"6","Total Tests":"2,511","Tests\/  1M pop ":"1,794","Continent":"North America"},"Mozambique":{"Total Cases":"115","New Cases":"+11","Total Deaths":" ","New Deaths":0,"Total Recovered":"35","Active Cases":"80","Serious\/Critical":0,"Tot Cases\/ 1M pop":"4","Deaths\/ 1M pop":0,"Total Tests":"5,119","Tests\/  1M pop ":"164","Continent":"Africa"},"Guyana":{"Total Cases":"113","New Cases":0,"Total Deaths":"10 ","New Deaths":0,"Total Recovered":"41","Active Cases":"62","Serious\/Critical":"3","Tot Cases\/ 1M pop":"144","Deaths\/ 1M pop":"13","Total Tests":"1,020","Tests\/  1M pop ":"1,297","Continent":"South America"},"Aruba":{"Total Cases":"101","New Cases":0,"Total Deaths":"3 ","New Deaths":0,"Total Recovered":"91","Active Cases":"7","Serious\/Critical":"4","Tot Cases\/ 1M pop":"946","Deaths\/ 1M pop":"28","Total Tests":"1,913","Tests\/  1M pop ":"17,918","Continent":"North America"},"Mongolia":{"Total Cases":"98","New Cases":"+56","Total Deaths":" ","New Deaths":0,"Total Recovered":"15","Active Cases":"83","Serious\/Critical":"2","Tot Cases\/ 1M pop":"30","Deaths\/ 1M pop":0,"Total Tests":"10,162","Tests\/  1M pop ":"3,100","Continent":"Asia"},"Monaco":{"Total Cases":"96","New Cases":0,"Total Deaths":"4 ","New Deaths":0,"Total Recovered":"87","Active Cases":"5","Serious\/Critical":"1","Tot Cases\/ 1M pop":"2,446","Deaths\/ 1M pop":"102","Total Tests":0,"Tests\/  1M pop ":0,"Continent":"Europe"},"Bahamas":{"Total Cases":"94","New Cases":0,"Total Deaths":"11 ","New Deaths":0,"Total Recovered":"41","Active Cases":"42","Serious\/Critical":"1","Tot Cases\/ 1M pop":"239","Deaths\/ 1M pop":"28","Total Tests":"1,670","Tests\/  1M pop ":"4,247","Continent":"North America"},"Cayman Islands":{"Total Cases":"86","New Cases":0,"Total Deaths":"1 ","New Deaths":0,"Total Recovered":"54","Active Cases":"31","Serious\/Critical":"3","Tot Cases\/ 1M pop":"1,309","Deaths\/ 1M pop":"15","Total Tests":"4,893","Tests\/  1M pop ":"74,450","Continent":"North America"},"Yemen":{"Total Cases":"85","New Cases":"+15","Total Deaths":"12 ","New Deaths":0,"Total Recovered":"1","Active Cases":"72","Serious\/Critical":0,"Tot Cases\/ 1M pop":"3","Deaths\/ 1M pop":"0.4","Total Tests":"120","Tests\/  1M pop ":"4","Continent":"Asia"},"Barbados":{"Total Cases":"85","New Cases":0,"Total Deaths":"7 ","New Deaths":0,"Total Recovered":"65","Active Cases":"13","Serious\/Critical":"4","Tot Cases\/ 1M pop":"296","Deaths\/ 1M pop":"24","Total Tests":"3,480","Tests\/  1M pop ":"12,110","Continent":"North America"},"Liechtenstein":{"Total Cases":"82","New Cases":0,"Total Deaths":"1 ","New Deaths":0,"Total Recovered":"55","Active Cases":"26","Serious\/Critical":0,"Tot Cases\/ 1M pop":"2,151","Deaths\/ 1M pop":"26","Total Tests":"900","Tests\/  1M pop ":"23,605","Continent":"Europe"},"Sint Maarten":{"Total Cases":"76","New Cases":0,"Total Deaths":"15 ","New Deaths":0,"Total Recovered":"46","Active Cases":"15","Serious\/Critical":"7","Tot Cases\/ 1M pop":"1,773","Deaths\/ 1M pop":"350","Total Tests":"329","Tests\/  1M pop ":"7,673","Continent":"North America"},"Libya":{"Total Cases":"64","New Cases":0,"Total Deaths":"3 ","New Deaths":0,"Total Recovered":"28","Active Cases":"33","Serious\/Critical":0,"Tot Cases\/ 1M pop":"9","Deaths\/ 1M pop":"0.4","Total Tests":"3,253","Tests\/  1M pop ":"473","Continent":"Africa"},"Malawi":{"Total Cases":"63","New Cases":0,"Total Deaths":"3 ","New Deaths":0,"Total Recovered":"24","Active Cases":"36","Serious\/Critical":"1","Tot Cases\/ 1M pop":"3","Deaths\/ 1M pop":"0.2","Total Tests":"1,363","Tests\/  1M pop ":"71","Continent":"Africa"},"French Polynesia":{"Total Cases":"60","New Cases":0,"Total Deaths":" ","New Deaths":0,"Total Recovered":"58","Active Cases":"2","Serious\/Critical":"1","Tot Cases\/ 1M pop":"214","Deaths\/ 1M pop":0,"Total Tests":"3,096","Tests\/  1M pop ":"11,021","Continent":"Australia\/Oceania"},"Syria":{"Total Cases":"48","New Cases":0,"Total Deaths":"3 ","New Deaths":0,"Total Recovered":"29","Active Cases":"16","Serious\/Critical":0,"Tot Cases\/ 1M pop":"3","Deaths\/ 1M pop":"0.2","Total Tests":0,"Tests\/  1M pop ":0,"Continent":"Asia"},"Angola":{"Total Cases":"48","New Cases":"+3","Total Deaths":"2 ","New Deaths":0,"Total Recovered":"14","Active Cases":"32","Serious\/Critical":0,"Tot Cases\/ 1M pop":"1","Deaths\/ 1M pop":"0.06","Total Tests":"6,136","Tests\/  1M pop ":"187","Continent":"Africa"},"Macao":{"Total Cases":"45","New Cases":0,"Total Deaths":" ","New Deaths":0,"Total Recovered":"43","Active Cases":"2","Serious\/Critical":"1","Tot Cases\/ 1M pop":"69","Deaths\/ 1M pop":0,"Total Tests":0,"Tests\/  1M pop ":0,"Continent":"Asia"},"Saint Martin":{"Total Cases":"39","New Cases":0,"Total Deaths":"3 ","New Deaths":0,"Total Recovered":"30","Active Cases":"6","Serious\/Critical":"1","Tot Cases\/ 1M pop":"1,009","Deaths\/ 1M pop":"78","Total Tests":0,"Tests\/  1M pop ":0,"Continent":"North America"},"Eritrea":{"Total Cases":"39","New Cases":0,"Total Deaths":" ","New Deaths":0,"Total Recovered":"38","Active Cases":"1","Serious\/Critical":0,"Tot Cases\/ 1M pop":"11","Deaths\/ 1M pop":0,"Total Tests":0,"Tests\/  1M pop ":0,"Continent":"Africa"},"Zimbabwe":{"Total Cases":"37","New Cases":0,"Total Deaths":"4 ","New Deaths":0,"Total Recovered":"12","Active Cases":"21","Serious\/Critical":0,"Tot Cases\/ 1M pop":"2","Deaths\/ 1M pop":"0.3","Total Tests":"20,537","Tests\/  1M pop ":"1,382","Continent":"Africa"},"Nicaragua":{"Total Cases":"25","New Cases":0,"Total Deaths":"8 ","New Deaths":0,"Total Recovered":"7","Active Cases":"10","Serious\/Critical":0,"Tot Cases\/ 1M pop":"4","Deaths\/ 1M pop":"1","Total Tests":0,"Tests\/  1M pop ":0,"Continent":"North America"},"Antigua and Barbuda":{"Total Cases":"25","New Cases":0,"Total Deaths":"3 ","New Deaths":0,"Total Recovered":"19","Active Cases":"3","Serious\/Critical":"1","Tot Cases\/ 1M pop":"255","Deaths\/ 1M pop":"31","Total Tests":"183","Tests\/  1M pop ":"1,869","Continent":"North America"},"Botswana":{"Total Cases":"24","New Cases":0,"Total Deaths":"1 ","New Deaths":0,"Total Recovered":"17","Active Cases":"6","Serious\/Critical":0,"Tot Cases\/ 1M pop":"10","Deaths\/ 1M pop":"0.4","Total Tests":"11,495","Tests\/  1M pop ":"4,888","Continent":"Africa"},"Timor-Leste":{"Total Cases":"24","New Cases":0,"Total Deaths":" ","New Deaths":0,"Total Recovered":"21","Active Cases":"3","Serious\/Critical":0,"Tot Cases\/ 1M pop":"18","Deaths\/ 1M pop":0,"Total Tests":"738","Tests\/  1M pop ":"560","Continent":"Asia"},"Gambia":{"Total Cases":"23","New Cases":0,"Total Deaths":"1 ","New Deaths":0,"Total Recovered":"10","Active Cases":"12","Serious\/Critical":0,"Tot Cases\/ 1M pop":"10","Deaths\/ 1M pop":"0.4","Total Tests":"1,341","Tests\/  1M pop ":"555","Continent":"Africa"},"Grenada":{"Total Cases":"21","New Cases":0,"Total Deaths":" ","New Deaths":0,"Total Recovered":"13","Active Cases":"8","Serious\/Critical":"4","Tot Cases\/ 1M pop":"187","Deaths\/ 1M pop":0,"Total Tests":"1,406","Tests\/  1M pop ":"12,495","Continent":"North America"},"Bhutan":{"Total Cases":"19","New Cases":"+8","Total Deaths":" ","New Deaths":0,"Total Recovered":"5","Active Cases":"14","Serious\/Critical":0,"Tot Cases\/ 1M pop":"25","Deaths\/ 1M pop":0,"Total Tests":"12,932","Tests\/  1M pop ":"16,760","Continent":"Asia"},"Laos":{"Total Cases":"19","New Cases":0,"Total Deaths":" ","New Deaths":0,"Total Recovered":"14","Active Cases":"5","Serious\/Critical":0,"Tot Cases\/ 1M pop":"3","Deaths\/ 1M pop":0,"Total Tests":"4,092","Tests\/  1M pop ":"562","Continent":"Asia"},"Belize":{"Total Cases":"18","New Cases":0,"Total Deaths":"2 ","New Deaths":0,"Total Recovered":"16","Active Cases":"0","Serious\/Critical":0,"Tot Cases\/ 1M pop":"45","Deaths\/ 1M pop":"5","Total Tests":"1,043","Tests\/  1M pop ":"2,623","Continent":"North America"},"Fiji":{"Total Cases":"18","New Cases":0,"Total Deaths":" ","New Deaths":0,"Total Recovered":"14","Active Cases":"4","Serious\/Critical":0,"Tot Cases\/ 1M pop":"20","Deaths\/ 1M pop":0,"Total Tests":"1,300","Tests\/  1M pop ":"1,450","Continent":"Australia\/Oceania"},"New Caledonia":{"Total Cases":"18","New Cases":0,"Total Deaths":" ","New Deaths":0,"Total Recovered":"18","Active Cases":"0","Serious\/Critical":0,"Tot Cases\/ 1M pop":"63","Deaths\/ 1M pop":0,"Total Tests":"5,454","Tests\/  1M pop ":"19,103","Continent":"Australia\/Oceania"},"Saint Lucia":{"Total Cases":"18","New Cases":0,"Total Deaths":" ","New Deaths":0,"Total Recovered":"18","Active Cases":"0","Serious\/Critical":0,"Tot Cases\/ 1M pop":"98","Deaths\/ 1M pop":0,"Total Tests":"727","Tests\/  1M pop ":"3,959","Continent":"North America"},"St. Vincent Grenadines":{"Total Cases":"17","New Cases":0,"Total Deaths":" ","New Deaths":0,"Total Recovered":"12","Active Cases":"5","Serious\/Critical":0,"Tot Cases\/ 1M pop":"153","Deaths\/ 1M pop":0,"Total Tests":"155","Tests\/  1M pop ":"1,397","Continent":"North America"},"Mauritania":{"Total Cases":"16","New Cases":"+1","Total Deaths":"2 ","New Deaths":0,"Total Recovered":"6","Active Cases":"8","Serious\/Critical":0,"Tot Cases\/ 1M pop":"3","Deaths\/ 1M pop":"0.4","Total Tests":"2,015","Tests\/  1M pop ":"433","Continent":"Africa"},"Cura\u00e7ao":{"Total Cases":"16","New Cases":0,"Total Deaths":"1 ","New Deaths":0,"Total Recovered":"14","Active Cases":"1","Serious\/Critical":0,"Tot Cases\/ 1M pop":"98","Deaths\/ 1M pop":"6","Total Tests":"389","Tests\/  1M pop ":"2,371","Continent":"North America"},"Dominica":{"Total Cases":"16","New Cases":0,"Total Deaths":" ","New Deaths":0,"Total Recovered":"15","Active Cases":"1","Serious\/Critical":0,"Tot Cases\/ 1M pop":"222","Deaths\/ 1M pop":0,"Total Tests":"420","Tests\/  1M pop ":"5,834","Continent":"North America"},"Namibia":{"Total Cases":"16","New Cases":0,"Total Deaths":" ","New Deaths":0,"Total Recovered":"12","Active Cases":"4","Serious\/Critical":0,"Tot Cases\/ 1M pop":"6","Deaths\/ 1M pop":0,"Total Tests":"2,011","Tests\/  1M pop ":"791","Continent":"Africa"},"Burundi":{"Total Cases":"15","New Cases":0,"Total Deaths":"1 ","New Deaths":0,"Total Recovered":"7","Active Cases":"7","Serious\/Critical":0,"Tot Cases\/ 1M pop":"1","Deaths\/ 1M pop":"0.08","Total Tests":"284","Tests\/  1M pop ":"24","Continent":"Africa"},"Saint Kitts and Nevis":{"Total Cases":"15","New Cases":0,"Total Deaths":" ","New Deaths":0,"Total Recovered":"14","Active Cases":"1","Serious\/Critical":0,"Tot Cases\/ 1M pop":"282","Deaths\/ 1M pop":0,"Total Tests":"327","Tests\/  1M pop ":"6,147","Continent":"North America"},"Falkland Islands":{"Total Cases":"13","New Cases":0,"Total Deaths":" ","New Deaths":0,"Total Recovered":"13","Active Cases":"0","Serious\/Critical":0,"Tot Cases\/ 1M pop":"3,736","Deaths\/ 1M pop":0,"Total Tests":"402","Tests\/  1M pop ":"115,517","Continent":"South America"},"Turks and Caicos":{"Total Cases":"12","New Cases":0,"Total Deaths":"1 ","New Deaths":0,"Total Recovered":"10","Active Cases":"1","Serious\/Critical":0,"Tot Cases\/ 1M pop":"310","Deaths\/ 1M pop":"26","Total Tests":"109","Tests\/  1M pop ":"2,815","Continent":"North America"},"Vatican City":{"Total Cases":"12","New Cases":0,"Total Deaths":" ","New Deaths":0,"Total Recovered":"2","Active Cases":"10","Serious\/Critical":0,"Tot Cases\/ 1M pop":"14,981","Deaths\/ 1M pop":0,"Total Tests":0,"Tests\/  1M pop ":0,"Continent":"Europe"},"Comoros":{"Total Cases":"11","New Cases":0,"Total Deaths":"1 ","New Deaths":0,"Total Recovered":0,"Active Cases":"10","Serious\/Critical":0,"Tot Cases\/ 1M pop":"13","Deaths\/ 1M pop":"1","Total Tests":0,"Tests\/  1M pop ":0,"Continent":"Africa"},"Montserrat":{"Total Cases":"11","New Cases":0,"Total Deaths":"1 ","New Deaths":0,"Total Recovered":"8","Active Cases":"2","Serious\/Critical":"1","Tot Cases\/ 1M pop":"2,204","Deaths\/ 1M pop":"200","Total Tests":"36","Tests\/  1M pop ":"7,212","Continent":"North America"},"Greenland":{"Total Cases":"11","New Cases":0,"Total Deaths":" ","New Deaths":0,"Total Recovered":"11","Active Cases":"0","Serious\/Critical":0,"Tot Cases\/ 1M pop":"194","Deaths\/ 1M pop":0,"Total Tests":"1,579","Tests\/  1M pop ":"27,814","Continent":"North America"},"Seychelles":{"Total Cases":"11","New Cases":0,"Total Deaths":" ","New Deaths":0,"Total Recovered":"10","Active Cases":"1","Serious\/Critical":0,"Tot Cases\/ 1M pop":"112","Deaths\/ 1M pop":0,"Total Tests":0,"Tests\/  1M pop ":0,"Continent":"Africa"},"Suriname":{"Total Cases":"10","New Cases":0,"Total Deaths":"1 ","New Deaths":0,"Total Recovered":"9","Active Cases":"0","Serious\/Critical":0,"Tot Cases\/ 1M pop":"17","Deaths\/ 1M pop":"2","Total Tests":"404","Tests\/  1M pop ":"689","Continent":"South America"},"MS Zaandam":{"Total Cases":"9","New Cases":0,"Total Deaths":"2 ","New Deaths":0,"Total Recovered":0,"Active Cases":"7","Serious\/Critical":0,"Tot Cases\/ 1M pop":0,"Deaths\/ 1M pop":0,"Total Tests":0,"Tests\/  1M pop ":0,"Continent":0},"Papua New Guinea":{"Total Cases":"8","New Cases":0,"Total Deaths":" ","New Deaths":0,"Total Recovered":"8","Active Cases":"0","Serious\/Critical":0,"Tot Cases\/ 1M pop":"0.9","Deaths\/ 1M pop":0,"Total Tests":"2,402","Tests\/  1M pop ":"268","Continent":"Australia\/Oceania"},"British Virgin Islands":{"Total Cases":"7","New Cases":0,"Total Deaths":"1 ","New Deaths":0,"Total Recovered":"4","Active Cases":"2","Serious\/Critical":0,"Tot Cases\/ 1M pop":"232","Deaths\/ 1M pop":"33","Total Tests":"167","Tests\/  1M pop ":"5,524","Continent":"North America"},"Caribbean Netherlands":{"Total Cases":"6","New Cases":0,"Total Deaths":" ","New Deaths":0,"Total Recovered":"6","Active Cases":"0","Serious\/Critical":0,"Tot Cases\/ 1M pop":"229","Deaths\/ 1M pop":0,"Total Tests":"357","Tests\/  1M pop ":"13,614","Continent":"North America"},"St. Barth":{"Total Cases":"6","New Cases":0,"Total Deaths":" ","New Deaths":0,"Total Recovered":"6","Active Cases":"0","Serious\/Critical":0,"Tot Cases\/ 1M pop":"607","Deaths\/ 1M pop":0,"Total Tests":0,"Tests\/  1M pop ":0,"Continent":"North America"},"Western Sahara":{"Total Cases":"6","New Cases":0,"Total Deaths":" ","New Deaths":0,"Total Recovered":"6","Active Cases":"0","Serious\/Critical":0,"Tot Cases\/ 1M pop":"10","Deaths\/ 1M pop":0,"Total Tests":0,"Tests\/  1M pop ":0,"Continent":"Africa"},"Anguilla":{"Total Cases":"3","New Cases":0,"Total Deaths":" ","New Deaths":0,"Total Recovered":"3","Active Cases":"0","Serious\/Critical":0,"Tot Cases\/ 1M pop":"200","Deaths\/ 1M pop":0,"Total Tests":0,"Tests\/  1M pop ":0,"Continent":"North America"},"Lesotho":{"Total Cases":"1","New Cases":0,"Total Deaths":" ","New Deaths":0,"Total Recovered":0,"Active Cases":"1","Serious\/Critical":0,"Tot Cases\/ 1M pop":"0.5","Deaths\/ 1M pop":0,"Total Tests":0,"Tests\/  1M pop ":0,"Continent":"Africa"},"Saint Pierre Miquelon":{"Total Cases":"1","New Cases":0,"Total Deaths":" ","New Deaths":0,"Total Recovered":"1","Active Cases":"0","Serious\/Critical":0,"Tot Cases\/ 1M pop":"173","Deaths\/ 1M pop":0,"Total Tests":0,"Tests\/  1M pop ":0,"Continent":"North America"},"China":{"Total Cases":"82,929","New Cases":"+3","Total Deaths":"4,633 ","New Deaths":0,"Total Recovered":"78,195","Active Cases":"101","Serious\/Critical":"9","Tot Cases\/ 1M pop":"58","Deaths\/ 1M pop":"3","Total Tests":0,"Tests\/  1M pop ":0,"Continent":"Asia"}}